PySimpleZscaler/__init__.py
PySimpleZscaler/zscaler.py
pysimplezscaler-0.1.2.dist-info/METADATA
pysimplezscaler-0.1.2.dist-info/WHEEL
pysimplezscaler-0.1.2.dist-info/licenses/LICENSE
pysimplezscaler-0.1.2.dist-info/RECORD
