Metadata-Version: 2.1
Name: PySimpleZscaler
Version: 0.1.2
Summary: A small wrapper for Zscaler API
Author-email: Błażej Szargut <blazejszargut@gmail.com>
Maintainer-email: Błażej Szargut <blazejszargut@gmail.com>
License-Expression: GPL-3.0-or-later
License-File: LICENSE
Requires-Python: >=3.7
